sightingdb/__init__.py
sightingdb/__version__.py
sightingdb/auth.py
sightingdb/connection.py
sightingdb/delete.py
sightingdb/read.py
sightingdb/write.py
sightingdb-0.0.6.dist-info/METADATA
sightingdb-0.0.6.dist-info/WHEEL
sightingdb-0.0.6.dist-info/top_level.txt
sightingdb-0.0.6.dist-info/RECORD
