Metadata-Version: 2.1
Name: sightingdb
Version: 0.0.6
Summary: The Python Client Library for SightingDB
Home-page: https://www.github.com/stricaud/sightingdb-client
Author: Sebastien Tricaud
Author-email: sebastien@honeynet.org
Maintainer: Sebastien Tricaud
Maintainer-email: sebastien@honeynet.org
License: MIT
Platform: UNKNOWN
Classifier: Programming Language :: Python :: 3
Classifier: License :: OSI Approved :: MIT License
Classifier: Operating System :: OS Independent
Requires-Dist: requests
